scheduler/__init__.py
scheduler/agent.py
scheduler/blocks.py
scheduler/scheduler.py
scheduler/storage.py
scheduler/example/normalWithTool.yaml
chatgpt_mirai_qq_bot_scheduler-0.3.9.dist-info/LICENSE
chatgpt_mirai_qq_bot_scheduler-0.3.9.dist-info/METADATA
chatgpt_mirai_qq_bot_scheduler-0.3.9.dist-info/WHEEL
chatgpt_mirai_qq_bot_scheduler-0.3.9.dist-info/entry_points.txt
chatgpt_mirai_qq_bot_scheduler-0.3.9.dist-info/top_level.txt
chatgpt_mirai_qq_bot_scheduler-0.3.9.dist-info/RECORD
