Metadata-Version: 2.1
Name: chatgpt-mirai-qq-bot-scheduler
Version: 0.3.9
Summary: 定时任务 for lss233/chatgpt-mirai-qq-bot，提供聚合block实现定时任务的增删查(同时也可以配置其他安装的block实现自动调用)
Home-page: https://github.com/chuanSir123/scheduler
Author: chuanSir
Author-email: 416448943@qq.com
Project-URL: Bug Tracker, https://github.com/chuanSir123/scheduler/issues
Project-URL: Documentation, https://github.com/chuanSir123/scheduler/wiki
Project-URL: Source Code, https://github.com/chuanSir123/scheduler
Classifier: Programming Language :: Python :: 3
Classifier: License :: OSI Approved :: GNU Affero General Public License v3
Classifier: Operating System :: OS Independent
Requires-Python: >=3.8
License-File: LICENSE
Requires-Dist: apscheduler
Requires-Dist: kirara-ai>3.2.0
